{
  "appPageId" : "24027472-c4c9-467a-aa1c-a7c3f9ef04ec",
  "componentName" : "siteforce:sldsOneColLayout",
  "dataProviders" : [ ],
  "id" : "d5a8bebf-9a32-4413-b156-bd8616c3098d",
  "label" : "User Settings",
  "regions" : [ {
    "id" : "ba01a740-9608-4d06-9a96-bc17c24a917c",
    "regionName" : "header",
    "type" : "region"
  }, {
    "components" : [ {
      "componentAttributes" : {
        "accountSectionTitle" : "Account",
        "accountTabName" : "Account Management",
        "connectedSourcesTabName" : "Connected Sources",
        "deleteAccountButtonTitle" : "Deactivate My Account",
        "deleteAccountConfirmationPopupBody" : "After you deactivate your account, you'll lose access to this site.",
        "deleteAccountConfirmationPopupButtonTitle" : "Got It",
        "deleteAccountConfirmationPopupTitle" : "Deactivate your account?",
        "deleteAccountErrorMessage" : "Something went wrong. Contact your site administrator.",
        "deleteAccountSectionTitle" : "Deactivate Account",
        "emailNotificationsTitle" : "Email Notifications",
        "emailSectionDescText" : "When email notifications are enabled, email me when someone:",
        "hideAccountDeleteSection" : true,
        "hideChatterNotificationSettings" : false,
        "hideConnectedSources" : false,
        "hideEmailNotificationSettings" : false,
        "hideProfileVisibilitySettings" : false,
        "id" : "{!recordId}",
        "locationTitle" : "Location",
        "profileSectionDescText" : "Customize who is able to see what on your profile page",
        "profileSectionToolTipText" : "Restricted: Visible to the employees of the company that created the site. Members: Visible to logged-in members. Public: Visible to anyone viewing pages that don't require login.",
        "profileVisibilityTitle" : "Profile Visibility",
        "settingsPageTitle" : "My Settings"
      },
      "componentName" : "forceCommunity:userSettingsCustomizable",
      "id" : "6259715f-a4d4-4bf1-9d2d-568e18d3ec7f",
      "renderPriority" : "NEUTRAL",
      "renditionMap" : { },
      "type" : "component"
    } ],
    "id" : "7d38bd91-0262-4682-9067-880f12d646e4",
    "regionName" : "content",
    "type" : "region"
  }, {
    "id" : "07ca6e89-2b75-4ef8-be2c-e1cc007551f7",
    "regionName" : "footer",
    "type" : "region"
  } ],
  "themeLayoutType" : "Inner",
  "type" : "view",
  "viewType" : "usersettings"
}